HaiChatGPT/__init__.py
HaiChatGPT/env.py
HaiChatGPT/tt.py
HaiChatGPT/version.py
HaiChatGPT/apis/__init__.py
HaiChatGPT/apis/apis.py
HaiChatGPT/repos/__init__.py
HaiChatGPT/repos/ChatGPT/__init__.py
HaiChatGPT/repos/ChatGPT/setup.py
HaiChatGPT/repos/ChatGPT/src/__init__.py
HaiChatGPT/repos/ChatGPT/src/revChatGPT/GPTserver.py
HaiChatGPT/repos/ChatGPT/src/revChatGPT/Official.py
HaiChatGPT/repos/ChatGPT/src/revChatGPT/Unofficial.py
HaiChatGPT/repos/ChatGPT/src/revChatGPT/__init__.py
HaiChatGPT/repos/ChatGPT/src/revChatGPT/__main__.py
HaiChatGPT/repos/PyChatGPT/__init__.py
HaiChatGPT/repos/PyChatGPT/src/__init__.py
HaiChatGPT/repos/PyChatGPT/src/pychatgpt/__init__.py
HaiChatGPT/repos/PyChatGPT/src/pychatgpt/main.py
HaiChatGPT/src/__init__.py
HaiChatGPT/src/hai_chat_gpt.py
HaiChatGPT/src/cli/__init__.py
HaiChatGPT/src/cli/cli.py
HaiChatGPT/src/ui/__init__.py
hai_chat_gpt-0.0.8.dist-info/METADATA
hai_chat_gpt-0.0.8.dist-info/WHEEL
hai_chat_gpt-0.0.8.dist-info/entry_points.txt
hai_chat_gpt-0.0.8.dist-info/top_level.txt
hai_chat_gpt-0.0.8.dist-info/RECORD
