Metadata-Version: 2.1
Name: hai-chat-gpt
Version: 0.0.8
Summary: ChatGPT implementation in Hakutaku Artificial Intelligence (HAI) Platform.
Home-page: https://github.com/zhangzhengde0225/HaiChatGPT
Author: Zhengde Zhang
Author-email: drivener@163.com
License: MIT
Classifier: License :: OSI Approved :: MIT License
Classifier: Programming Language :: Python
Classifier: Programming Language :: Python :: 3
Classifier: Programming Language :: Python :: 3.6
Classifier: Programming Language :: Python :: 3.7
Classifier: Programming Language :: Python :: 3.8
Classifier: Programming Language :: Python :: 3.9
Classifier: Programming Language :: Python :: Implementation :: CPython
Classifier: Programming Language :: Python :: Implementation :: PyPy
Requires-Python: >=3.6.0
Requires-Dist: openai
Requires-Dist: tiktoken
Requires-Dist: pillow
Requires-Dist: pyyaml
Requires-Dist: damei
Requires-Dist: numpy
Requires-Dist: easydict
